setup.py
wolphin/__init__.py
wolphin/attribute_dict.py
wolphin/config.py
wolphin/exceptions.py
wolphin/generator.py
wolphin/project.py
wolphin/selector.py
wolphin.egg-info/PKG-INFO
wolphin.egg-info/SOURCES.txt
wolphin.egg-info/dependency_links.txt
wolphin.egg-info/requires.txt
wolphin.egg-info/top_level.txt