Metadata-Version: 1.0
Name: wolphin
Version: 1.0
Summary: Wolphin is a cousin of Boto. It can manage Amazon ec2 instances for your project.
Home-page: http://www.locationlabs.com
Author: Location Labs
Author-email: info@locationlabs.com
License: UNKNOWN
Platform: UNKNOWN
